tfrecord_slow/__init__.py
tfrecord_slow/__main__.py
tfrecord_slow/reader.py
tfrecord_slow/writer.py
tfrecord_slow/loaders/__init__.py
tfrecord_slow/loaders/msgpack_loader.py
tfrecord_slow/loaders/raw_loader.py
tfrecord_slow/utils/__init__.py
tfrecord_slow/utils/masked_crc.py
tfrecord_slow/utils/msgpack.py
tfrecord_slow/utils/numpy.py
tfrecord_slow-0.6.0.dist-info/METADATA
tfrecord_slow-0.6.0.dist-info/WHEEL
tfrecord_slow-0.6.0.dist-info/entry_points.txt
tfrecord_slow-0.6.0.dist-info/licenses/LICENSE
tfrecord_slow-0.6.0.dist-info/RECORD
