Metadata-Version: 2.3
Name: tfrecord-slow
Version: 0.6.0
Summary: TFRecord reader and writer without protobuf.
Author-email: SunDoge <triplez0@outlook.com>
License-File: LICENSE
Requires-Python: >=3.9
Provides-Extra: cli
Requires-Dist: loguru>=0.7.2; extra == 'cli'
Requires-Dist: tqdm>=4.66.2; extra == 'cli'
Provides-Extra: crc32c
Requires-Dist: crc32c>=2.4; extra == 'crc32c'
Requires-Dist: numpy>=1; extra == 'crc32c'
Provides-Extra: msgpack
Requires-Dist: msgspec>=0.18.6; extra == 'msgpack'
